lattix/__init__.py
lattix/__main__.py
lattix/py.typed
lattix/adapters/__init__.py
lattix/adapters/numpy.py
lattix/adapters/pandas.py
lattix/adapters/registry.py
lattix/adapters/registry.pyi
lattix/adapters/torch.py
lattix/adapters/xarray.py
lattix/core/__init__.py
lattix/core/base.py
lattix/core/base.pyi
lattix/core/interfaces.py
lattix/core/meta.py
lattix/core/mixins.py
lattix/core/mixins.pyi
lattix/serialization/__init__.py
lattix/serialization/json.py
lattix/serialization/msgpack.py
lattix/serialization/yaml.py
lattix/serialization/yaml.pyi
lattix/structures/__init__.py
lattix/structures/mapping.py
lattix/structures/mapping.pyi
lattix/utils/__init__.py
lattix/utils/_typing.py
lattix/utils/compat.py
lattix/utils/constant.py
lattix/utils/exceptions.py
lattix/utils/inspection.py
lattix/utils/path.py
lattix/utils/text.py
lattix/utils/transform.py
lattix/utils/types.py
py_lattix-0.2.1.dist-info/METADATA
py_lattix-0.2.1.dist-info/WHEEL
py_lattix-0.2.1.dist-info/licenses/LICENSE
py_lattix-0.2.1.dist-info/RECORD
