Metadata-Version: 2.4
Name: py-lattix
Version: 0.2.1
Summary: A high-performance, hierarchical, thread-safe mapping library for Python.
Project-URL: Homepage, https://github.com/YuHao-Yeh/Lattix
Project-URL: Documentation, https://github.com/YuHao-Yeh/Lattix#readme
Project-URL: Repository, https://github.com/YuHao-Yeh/Lattix
Project-URL: Issues, https://github.com/YuHao-Yeh/Lattix/issues
Author-email: Yeh Yuhao <yuhao200.ok@gmail.com>
License: BSD 3-Clause License
License-File: LICENSE
Keywords: attrdict,config,dot-access,hierarchical,mapping,thread-safe
Classifier: Development Status :: 5 - Production/Stable
Classifier: Intended Audience :: Developers
Classifier: Intended Audience :: Science/Research
Classifier: License :: OSI Approved :: BSD License
Classifier: Operating System :: OS Independent
Classifier: Programming Language :: Python
Classifier: Programming Language :: Python :: 3
Classifier: Programming Language :: Python :: 3.8
Classifier: Programming Language :: Python :: 3.9
Classifier: Programming Language :: Python :: 3.10
Classifier: Programming Language :: Python :: 3.11
Classifier: Programming Language :: Python :: 3.12
Classifier: Programming Language :: Python :: 3.13
Classifier: Topic :: Scientific/Engineering
Classifier: Topic :: Software Development :: Libraries :: Python Modules
Classifier: Typing :: Typed
Requires-Python: >=3.8
Requires-Dist: typing-extensions>=4.0; python_version <= '3.10'
Provides-Extra: check
Requires-Dist: mypy>=1.11; extra == 'check'
Requires-Dist: ruff; extra == 'check'
Requires-Dist: types-pyyaml; extra == 'check'
Provides-Extra: dev
Requires-Dist: black; extra == 'dev'
Requires-Dist: msgpack>=1.0; extra == 'dev'
Requires-Dist: mypy>=1.11; extra == 'dev'
Requires-Dist: nox; extra == 'dev'
Requires-Dist: numpy; extra == 'dev'
Requires-Dist: orjson>=3.0; extra == 'dev'
Requires-Dist: pandas; extra == 'dev'
Requires-Dist: pre-commit; extra == 'dev'
Requires-Dist: pytest; extra == 'dev'
Requires-Dist: pytest-cov; extra == 'dev'
Requires-Dist: pyyaml>=6.0; extra == 'dev'
Requires-Dist: ruff; extra == 'dev'
Requires-Dist: types-pyyaml; extra == 'dev'
Requires-Dist: typing-extensions>=4.0; extra == 'dev'
Provides-Extra: full
Requires-Dist: msgpack>=1.0; extra == 'full'
Requires-Dist: numpy; extra == 'full'
Requires-Dist: orjson>=3.0; extra == 'full'
Requires-Dist: pandas; extra == 'full'
Requires-Dist: pyyaml>=6.0; extra == 'full'
Provides-Extra: msgpack
Requires-Dist: msgpack>=1.0; extra == 'msgpack'
Provides-Extra: orjson
Requires-Dist: orjson>=3.0; extra == 'orjson'
Provides-Extra: test
Requires-Dist: msgpack>=1.0; extra == 'test'
Requires-Dist: numpy; extra == 'test'
Requires-Dist: orjson>=3.0; extra == 'test'
Requires-Dist: pandas; extra == 'test'
Requires-Dist: pytest; extra == 'test'
Requires-Dist: pytest-cov; extra == 'test'
Requires-Dist: pyyaml>=6.0; extra == 'test'
Requires-Dist: typing-extensions>=4.0; extra == 'test'
Provides-Extra: torch
Requires-Dist: torch; extra == 'torch'
Provides-Extra: xarray
Requires-Dist: xarray; extra == 'xarray'
Provides-Extra: yaml
Requires-Dist: pyyaml>=6.0; extra == 'yaml'
